evaluation/__init__.py
evaluation/benchmarks.py
evaluation/data.py
evaluation/evaluator.py
evaluation/metrics.py
evaluation/models.py
evaluation/precompute.py
evaluation/utils/__init__.py
evaluation/utils/env_utils.py
evaluation/utils/experiment_utils.py
evaluation/utils/lang_utils.py
evaluation/utils/logging_utils.py
evaluation/utils/tokenizer_utils.py
evaluation/utils/training_utils.py
evaluation/utils/typing.py
pastalib/__init__.py
pastalib/pasta.py
pastalib/utils/__init__.py
pastalib/utils/tokenizer_utils.py
pastalib/utils/typing.py
scripts/__init__.py
scripts/eval_bias_gen.py
scripts/eval_biasbios_instruction.py
scripts/eval_fact_gen.py
scripts/reformat_dataset.py
pastalib-0.1.3.dist-info/LICENSE
pastalib-0.1.3.dist-info/METADATA
pastalib-0.1.3.dist-info/WHEEL
pastalib-0.1.3.dist-info/top_level.txt
pastalib-0.1.3.dist-info/RECORD
