Metadata-Version: 2.1
Name: pastalib
Version: 0.1.3
Summary: PyTorch Implementation for PASTA, A Post-hoc Attention Steering Approach that enables users to emphasize specific contexts for LLMs.
Home-page: https://github.com/QingruZhang/PASTA
Author: Qingru Zhang, Chandan Singh, Lucas Liu, Xiaodong Liu, Bin Yu, Jianfeng Gao, Tuo Zhao
Author-email: qingru.zhang@gatech.edu
Classifier: Programming Language :: Python :: 3
Classifier: Programming Language :: Python :: 3.7
Classifier: Programming Language :: Python :: 3.8
Classifier: Programming Language :: Python :: 3.9
Classifier: Programming Language :: Python :: 3.10
Classifier: License :: OSI Approved :: MIT License
Classifier: Operating System :: OS Independent
Classifier: Topic :: Scientific/Engineering :: Artificial Intelligence
Requires-Python: >=3.7.0
License-File: LICENSE
Requires-Dist: transformers (>=4.31.1)
